pupg/__init__.py
pupg/_cli.py
pupg-0.0.2.dist-info/LICENSE.txt
pupg-0.0.2.dist-info/METADATA
pupg-0.0.2.dist-info/WHEEL
pupg-0.0.2.dist-info/entry_points.txt
pupg-0.0.2.dist-info/top_level.txt
pupg-0.0.2.dist-info/RECORD
