Metadata-Version: 2.1
Name: pupg
Version: 0.0.2
Summary: Upgrade all python packages.
Home-page: https://github.com/romanstrazanec/pupg
Author: Roman Stražanec
Author-email: strazanec.roman@gmail.com
Maintainer: Roman Stražanec
Maintainer-email: strazanec.roman@gmail.com
License: MIT
Download-URL: https://github.com/romanstrazanec/pupg/archive/v0.0.2.tar.gz
Keywords: pip install upgrade package all
Platform: UNKNOWN
Classifier: Development Status :: 4 - Beta
Classifier: Environment :: Console
Classifier: Intended Audience :: Developers
Classifier: Intended Audience :: System Administrators
Classifier: License :: OSI Approved :: MIT License
Classifier: Operating System :: OS Independent
Classifier: Programming Language :: Python :: 3.7
Classifier: Topic :: Other/Nonlisted Topic
Requires-Dist: pip
